foliotrack/__init__.py
foliotrack/domain/Portfolio.py
foliotrack/domain/Security.py
foliotrack/domain/ShareInfo.py
foliotrack/domain/__init__.py
foliotrack/services/BacktestService.py
foliotrack/services/MarketService.py
foliotrack/services/OptimizationService.py
foliotrack/services/__init__.py
foliotrack/storage/PortfolioRepository.py
foliotrack/storage/__init__.py
foliotrack/utils/Currency.py
foliotrack/utils/__init__.py
foliotrack-0.0.7.dist-info/licenses/LICENSE
tests/__init__.py
tests/foliotrack/test_backtest.py
tests/foliotrack/test_currency.py
tests/foliotrack/test_equilibrate.py
tests/foliotrack/test_market_service.py
tests/foliotrack/test_portfolio.py
tests/foliotrack/test_security.py
foliotrack-0.0.7.dist-info/METADATA
foliotrack-0.0.7.dist-info/WHEEL
foliotrack-0.0.7.dist-info/top_level.txt
foliotrack-0.0.7.dist-info/RECORD
