Metadata-Version: 2.4
Name: foliotrack
Version: 0.0.7
Summary: Tool to keep balance a portfolio of securities while investing.
License-Expression: Apache-2.0
Project-URL: Homepage, https://github.com/PhDFlo/foliotrack
Project-URL: Bug Tracker, https://github.com/PhDFlo/foliotrack/issues
Keywords: portfolio,management,portfolio management,track,investment
Requires-Python: >=3.11
License-File: LICENSE
Requires-Dist: numpy
Requires-Dist: pyscipopt
Requires-Dist: cvxpy
Requires-Dist: pandas
Requires-Dist: yfinance
Requires-Dist: ecbdata
Requires-Dist: pytest
Requires-Dist: bt
Dynamic: license-file
